setup.py
tkitText/__init__.py
tkitText/text.py
tkitText.egg-info/PKG-INFO
tkitText.egg-info/SOURCES.txt
tkitText.egg-info/dependency_links.txt
tkitText.egg-info/requires.txt
tkitText.egg-info/top_level.txt