Metadata-Version: 2.1
Name: tkitText
Version: 0.0.1.5
Summary: Terry toolkit
Home-page: https://terry-toolkit.terrychan.org/zh/master/
Author: Terry Chan
Author-email: napoler2008@gmail.com
License: UNKNOWN
Platform: UNKNOWN
